{
    "bricks": [
        {
            "type": 1,
            "x": 420,
            "y": 250
        },
        {
            "type": 1,
            "x": 580,
            "y": 250
        },
        {
            "type": 1,
            "x": 420,
            "y": 690
        },
        {
            "type": 1,
            "x": 580,
            "y": 690
        },
        {
            "type": 1,
            "x": 740,
            "y": 690
        },
        {
            "type": 1,
            "x": 900,
            "y": 690
        },
        {
            "type": 1,
            "x": 1060,
            "y": 690
        },
        {
            "type": 1,
            "x": 1220,
            "y": 690
        },
        {
            "type": 1,
            "x": 1380,
            "y": 690
        },
        {
            "type": 1,
            "x": 740,
            "y": 250
        },
        {
            "type": 1,
            "x": 900,
            "y": 250
        },
        {
            "type": 1,
            "x": 1060,
            "y": 250
        },
        {
            "type": 1,
            "x": 1220,
            "y": 250
        },
        {
            "type": 1,
            "x": 1380,
            "y": 250
        }
    ]
}